cofutils/__init__.py
cofutils/cofprofiler.py
cofutils/cofwriter.py
cofutils/torch_version.py
cofutils/cofrun/__init__.py
cofutils/cofrun/common.py
cofutils/cofrun/dispatch.py
cofutils/parse/__init__.py
cofutils/parse/__main__.py
cofutils/parse/db.py
cofutils/parse/kernel.py
cofutils/parse/nsight.py
cofutils/parse/nvvp.py
cofutils/parse/parse.py
cofutils-1.2.0.dist-info/METADATA
cofutils-1.2.0.dist-info/WHEEL
cofutils-1.2.0.dist-info/entry_points.txt
cofutils-1.2.0.dist-info/top_level.txt
cofutils-1.2.0.dist-info/RECORD
