Metadata-Version: 2.1
Name: cofutils
Version: 1.2.0
Summary: Experiment toolkits
Home-page: https://gitee.com/haiqwa/cofutils.git
Author: whq1516@mail.ustc.edu.cn
Maintainer: whq1516@mail.ustc.edu.cn
License: See https://gitee.com/haiqwa/cofutils/blob/main/LICENSE
Requires-Python: >=3.6
Requires-Dist: torch
Requires-Dist: colorful
Requires-Dist: tensorboard
Requires-Dist: cxxfilt
Requires-Dist: packaging
Requires-Dist: tabulate
